phlorest/__init__.py
phlorest/__main__.py
phlorest/beast.py
phlorest/check.R
phlorest/check.py
phlorest/cldfwriter.py
phlorest/dataset.py
phlorest/metadata.py
phlorest/nexuslib.py
phlorest/scaffold.py
phlorest/commands/__init__.py
phlorest/commands/check.py
phlorest/commands/contrib.py
phlorest/commands/merge_characters.py
phlorest/commands/new.py
phlorest/commands/release.py
phlorest/phlorest_template/CONTRIBUTORS.md
phlorest/phlorest_template/cldfbench_+id+.py_tmpl
phlorest/phlorest_template/setup.cfg
phlorest/phlorest_template/setup.py_tmpl
phlorest/phlorest_template/test.py
phlorest/phlorest_template/.github/workflows/cldf-validation.yml
phlorest/phlorest_template/etc/characters.csv
phlorest/phlorest_template/etc/taxa.csv
phlorest/phlorest_template/raw/sources.bib
phlorest-1.7.1.dist-info/LICENSE
phlorest-1.7.1.dist-info/METADATA
phlorest-1.7.1.dist-info/WHEEL
phlorest-1.7.1.dist-info/entry_points.txt
phlorest-1.7.1.dist-info/top_level.txt
phlorest-1.7.1.dist-info/RECORD
