Metadata-Version: 2.1
Name: phlorest
Version: 1.7.1
Summary: A cldfbench plugin to curate language phylogenies
Home-page: https://github.com/phlorest/phlorest
Author: Simon Greenhill and Robert Forkel
Author-email: dlce.rdm@eva.mpg.de
License: Apache 2.0
Project-URL: Bug Tracker, https://github.com/phlorest/phlorest/issues
Keywords: cldf
Platform: any
Classifier: Development Status :: 2 - Pre-Alpha
Classifier: Intended Audience :: Developers
Classifier: Natural Language :: English
Classifier: Operating System :: OS Independent
Classifier: Programming Language :: Python :: 3
Classifier: Programming Language :: Python :: 3.9
Classifier: Programming Language :: Python :: 3.10
Classifier: Programming Language :: Python :: 3.11
Classifier: Programming Language :: Python :: 3.12
Classifier: Programming Language :: Python :: 3.13
Classifier: License :: OSI Approved :: Apache Software License
Requires-Python: >=3.9
License-File: LICENSE
Requires-Dist: newick>=1.9
Requires-Dist: commonnexus>=1.9
Requires-Dist: cldfviz>=0.10
Requires-Dist: pycldf>=1.33.0
Requires-Dist: clldutils
Requires-Dist: cldfbench>=1.10.0
Requires-Dist: cldfcatalog
Requires-Dist: attrs
Requires-Dist: pyglottolog>=3.9.0
Requires-Dist: termcolor
Provides-Extra: dev
Requires-Dist: flake8; extra == "dev"
Requires-Dist: wheel; extra == "dev"
Requires-Dist: build; extra == "dev"
Requires-Dist: twine; extra == "dev"
Provides-Extra: test
Requires-Dist: pyglottolog; extra == "test"
Requires-Dist: pytest>=5; extra == "test"
Requires-Dist: pytest-mock; extra == "test"
Requires-Dist: pytest-cov; extra == "test"
Requires-Dist: newick; extra == "test"
Requires-Dist: numpy; extra == "test"
